libnncase.modules.k510.so
libnncase.targets.k510.so
nncase_k510.libs/libgcc_s-a843a011.so.1
nncase_k510.libs/libstdc++-d54d9843.so.6.0.28
nncase_k510-1.9.0.20230323.dist-info/RECORD
nncase_k510-1.9.0.20230323.dist-info/LICENSE
nncase_k510-1.9.0.20230323.dist-info/WHEEL
nncase_k510-1.9.0.20230323.dist-info/top_level.txt
nncase_k510-1.9.0.20230323.dist-info/METADATA
nncase_k510-1.9.0.20230323.data/purelib/nncase_k510/__init__.py
