Metadata-Version: 2.1
Name: nncase-k510
Version: 1.9.0.20230323
Summary: k510 plug-in for nncase
Author: sunnycase
Author-email: guohui@canaan-creative.com
Maintainer: sunnycase
Maintainer-email: guohui@canaan-creative.com
License: 
Project-URL: Homepage, https://g.b-bug.org/maix2-ai-sw/k510-gnne-compiler
Project-URL: documentation, https://g.b-bug.org/maix2-ai-sw/k510-gnne-compiler
Project-URL: repository, https://g.b-bug.org/maix2-ai-sw/k510-gnne-compiler
Keywords: kendryte,nn,compiler,k510
Classifier: Programming Language :: C++
Classifier: Programming Language :: Python :: 3
Classifier: Programming Language :: Python :: 3.6
Classifier: Programming Language :: Python :: 3.7
Classifier: Programming Language :: Python :: 3.8
Classifier: Programming Language :: Python :: 3.9
Classifier: License :: OSI Approved :: Apache Software License
Classifier: Operating System :: OS Independent
Requires-Python: >=3.6
License-File: LICENSE
Requires-Dist: nncase (>=1.9.0)
